meraki_exception/__init__.py
meraki_exception/exception.py
meraki_exception-0.1.1.dist-info/WHEEL
meraki_exception-0.1.1.dist-info/METADATA
meraki_exception-0.1.1.dist-info/RECORD
