Metadata-Version: 2.1
Name: meraki-exception
Version: 0.1.1
Summary: 
Author: Thomas Christory
Requires-Python: >=3.8,<4.0
Classifier: Programming Language :: Python :: 3
Classifier: Programming Language :: Python :: 3.8
Classifier: Programming Language :: Python :: 3.9
Requires-Dist: meraki (>=1.4.3,<2.0.0)
Requires-Dist: rich (>=10.10.0,<11.0.0)
